scorepower.py
setup.py
config/__init__.py
config/config.py
config/parameters.py
dataProcessor/__init__.py
dataProcessor/binCut.py
dataProcessor/dataReports.py
dataProcessor/featurTools.py
dataProcessor/iDataProcessor.py
defaultPipeline/__init__.py
defaultPipeline/catboostTrianPipeline.py
defaultPipeline/lgbTrianPipeline.py
defaultPipeline/lrTrianPipeline.py
defaultPipeline/mlpTrianPipeline.py
defaultPipeline/predictPipeline.py
defaultPipeline/psiCalPipeline.py
modelProcessor/__init__.py
modelProcessor/iModels.py
modelProcessor/iTrain.py
modelProcessor/iValidator.py
modelProcessor/modelSelector.py
modelProcessor/performance.py
pipelineHandler/__init__.py
pipelineHandler/handlerFactory.py
pipelineHandler/pipelineCreator.py
pipelineHandler/pipelineExecutor.py
pipelineHandler/executorHandler/__init__.py
pipelineHandler/executorHandler/catboostExecutors.py
pipelineHandler/executorHandler/executors.py
pipelineHandler/executorHandler/lgbTrainExecutors.py
pipelineHandler/executorHandler/lrTrainExecutors.py
pipelineHandler/executorHandler/mlpTrainExecutors.py
pipelineHandler/executorHandler/psiExecutors.py
scorepower.egg-info/PKG-INFO
scorepower.egg-info/SOURCES.txt
scorepower.egg-info/dependency_links.txt
scorepower.egg-info/top_level.txt
workThread/__init__.py