Metadata-Version: 1.0
Name: scorepower
Version: 0.1.1
Summary: time and path tool
Home-page: https://github.com/xxlest
Author: bruce
Author-email: 85089081@qq.com
License: MIT Licence
Keywords: pip,scorepower
Platform: any
